Workbook

Sheet Summary
A1: AAPL Operating Model
A3: Ticker | B3: AAPL | C3: Recommendation | D3: Buy / Long | E3: Base $/sh | F3: ='Sensitivity'!D5 -> 220 | G3: Date | H3: 46130.412
A5: Scenario | B5: Revenue Growth | C5: Operating Margin | D5: Implied $/sh | E5: Vs. Base
A6: ='Sensitivity'!A4 -> Bear | B6: ='Sensitivity'!B4 -> 0.01 | C6: ='Sensitivity'!C4 -> 0.28 | D6: ='Sensitivity'!D4 -> 170 | E6: =IF($D$6=0,0,$D6/'Sensitivity'!D5-1) -> -0.22727273
A7: ='Sensitivity'!A5 -> Base | B7: ='Sensitivity'!B5 -> 0.035 | C7: ='Sensitivity'!C5 -> 0.315 | D7: ='Sensitivity'!D5 -> 220 | E7: =IF($D$7=0,0,$D7/'Sensitivity'!D5-1) -> 0
A8: ='Sensitivity'!A6 -> Bull | B8: ='Sensitivity'!B6 -> 0.055 | C8: ='Sensitivity'!C6 -> 0.34 | D8: ='Sensitivity'!D6 -> 260 | E8: =IF($D$8=0,0,$D8/'Sensitivity'!D5-1) -> 0.18181818
A10: Core Drivers | B10: FY2024 | C10: FY1 | D10: FY2 | E10: FY3 | F10: FY4
A11: Revenue ($mm) | B11: ='Operating Model'!B4 -> 391035 | C11: ='Operating Model'!C4 -> 401700 | D11: ='Operating Model'!D4 -> 415760 | E11: ='Operating Model'!E4 -> 432390 | F11: ='Operating Model'!F4 -> 449685
A12: Revenue Growth | B12: ='Operating Model'!B5 -> 0.020219941 | C12: ='Operating Model'!C5 -> 0.03 | D12: ='Operating Model'!D5 -> 0.035 | E12: ='Operating Model'!E5 -> 0.04 | F12: ='Operating Model'!F5 -> 0.04
A13: Gross Margin | B13: ='Operating Model'!B6 -> 0.4620635 | C13: ='Operating Model'!C6 -> 0.452 | D13: ='Operating Model'!D6 -> 0.454 | E13: ='Operating Model'!E6 -> 0.456 | F13: ='Operating Model'!F6 -> 0.456
A14: Operating Margin | B14: ='Operating Model'!B8 -> 0.31510223 | C14: ='Operating Model'!C8 -> 0.312 | D14: ='Operating Model'!D8 -> 0.314 | E14: ='Operating Model'!E8 -> 0.316 | F14: ='Operating Model'!F8 -> 0.317
A15: FCF Margin | B15: ='Operating Model'!B10 -> 0.27825386 | C15: ='Operating Model'!C10 -> 0.272 | D15: ='Operating Model'!D10 -> 0.274 | E15: ='Operating Model'!E10 -> 0.276 | F15: ='Operating Model'!F10 -> 0.277
A16: FCF ($mm) | B16: ='Operating Model'!B11 -> 108807 | C16: ='Operating Model'!C11 -> 109262.4 | D16: ='Operating Model'!D11 -> 113918.24 | E16: ='Operating Model'!E11 -> 119339.64 | F16: ='Operating Model'!F11 -> 124562.75
A18: Comps Snapshot | B18: EV/Revenue | C18: EV/EBITDA | D18: P/E | E18: P/E vs. Median
A19: =Comps!A4 -> MSFT | B19: =Comps!C4 -> 12.2 | C19: =Comps!D4 -> 24.5 | D19: =Comps!E4 -> 31.1 | E19: =IF(MEDIAN(Comps!E4:E6)=0,0,D19/MEDIAN(Comps!E4:E6)-1) -> 0.37610619
A20: =Comps!A5 -> GOOGL | B20: =Comps!C5 -> 5.9 | C20: =Comps!D5 -> 15.2 | D20: =Comps!E5 -> 21.4 | E20: =IF(MEDIAN(Comps!E4:E6)=0,0,D20/MEDIAN(Comps!E4:E6)-1) -> -0.053097345
A21: =Comps!A6 -> META | B21: =Comps!C6 -> 7.4 | C21: =Comps!D6 -> 14.1 | D21: =Comps!E6 -> 22.6 | E21: =IF(MEDIAN(Comps!E4:E6)=0,0,D21/MEDIAN(Comps!E4:E6)-1) -> 0
A23: Median EV/Revenue | B23: =MEDIAN(Comps!C4:C6) -> 7.4 | C23: Median P/E | D23: =MEDIAN(Comps!E4:E6) -> 22.6 | E23: FY4 Revenue | F23: ='Operating Model'!F4 -> 449685 | G23: FY4 FCF Margin | H23: ='Operating Model'!F10 -> 0.277

Sheet Inputs
A1: AAPL Inputs
A3: Input | B3: Value | C3: Source
A4: Narrative driver: What changed | B4: Apple reported FY2024 net sales of $391.0B. | C4: Apple FY2024 Form 10-K; cached SEC snapshot (2024-11-01)
A5: Narrative driver: Management / filing narrative | B5: FY2024 revenue returned to modest growth after FY2023 contraction. | C5: Apple FY2024 Form 10-K; cached SEC snapshot (2024-11-01)
A6: Reported Revenue Base | B6: $391.0bn | C6: Apple FY2024 Form 10-K; cached SEC snapshot
A7: Reported Gross Margin | B7: 46.2% | C7: Apple FY2024 Form 10-K; cached SEC snapshot
A8: Reported Operating Margin | B8: 31.5% | C8: Apple FY2024 Form 10-K; cached SEC snapshot
A9: Reported FCF Margin | B9: 27.8% | C9: Apple FY2024 Form 10-K; cached SEC snapshot
A10: Reported Revenue Base | B10: $391.0bn | C10: Apple FY2024 Form 10-K
A11: Reported Gross Margin | B11: 46.2% | C11: Apple FY2024 Form 10-K
A12: Reported Operating Margin | B12: 31.5% | C12: Apple FY2024 Form 10-K
A13: Reported FCF Margin | B13: 27.8% | C13: Apple FY2024 Form 10-K

Sheet Operating Model
A1: AAPL Operating Model
A3: $mm except per-share data | B3: FY2024 | C3: FY1 | D3: FY2 | E3: FY3 | F3: FY4
A4: Revenue ($mm) | B4: 391035 | C4: =B4*(1+C5) | D4: =C4*(1+D5) | E4: =D4*(1+E5) | F4: =E4*(1+F5)
A5: Revenue Growth | B5: 0.020219941 | C5: 0.03 | D5: 0.035 | E5: 0.04 | F5: 0.04
A6: Gross Margin | B6: 0.4620635 | C6: 0.452 | D6: 0.454 | E6: 0.456 | F6: 0.456
A7: Gross Profit ($mm) | B7: =B4*B6 | C7: =C4*C6 | D7: =D4*D6 | E7: =E4*E6 | F7: =F4*F6
A8: Operating Margin | B8: 0.31510223 | C8: 0.312 | D8: 0.314 | E8: 0.316 | F8: 0.317
A9: Operating Income ($mm) | B9: =B4*B8 | C9: =C4*C8 | D9: =D4*D8 | E9: =E4*E8 | F9: =F4*F8
A10: FCF Margin | B10: 0.27825386 | C10: 0.272 | D10: 0.274 | E10: 0.276 | F10: 0.277
A11: Free Cash Flow ($mm) | B11: =B4*B10 | C11: =C4*C10 | D11: =D4*D10 | E11: =E4*E10 | F11: =F4*F10

Sheet Sensitivity
A1: AAPL Sensitivity
A3: Case | B3: Revenue Growth | C3: Operating Margin | D3: Implied Value
A4: Bear | B4: 0.01 | C4: 0.28 | D4: 170
A5: Base | B5: 0.035 | C5: 0.315 | D5: 220
A6: Bull | B6: 0.055 | C6: 0.34 | D6: 260

Sheet Valuation
A1: AAPL Valuation Output
A3: Output | B3: $ / share | C3: Source
A4: Base Case Value | B4: 220 | C4: Forward estimate from reported baseline
A5: Bull Case Value | B5: 260 | C5: Forward estimate from reported baseline
A6: Bear Case Value | B6: 170 | C6: Forward estimate from reported baseline

Sheet Comps
A1: AAPL Comparable Companies
A3: Ticker | B3: Company | C3: EV/Revenue | D3: EV/EBITDA | E3: P/E | F3: Rationale
A4: MSFT | B4: Microsoft | C4: 12.2 | D4: 24.5 | E4: 31.1 | F4: Source: peer classification; mega-cap quality growth peer.
A5: GOOGL | B5: Alphabet | C5: 5.9 | D5: 15.2 | E5: 21.4 | F5: Source: peer classification; mega-cap platform peer.
A6: META | B6: Meta Platforms | C6: 7.4 | D6: 14.1 | E6: 22.6 | F6: Source: peer classification; mega-cap consumer technology peer.

Sheet Risk Triggers
A1: AAPL Risk / Falsification
A3: Trigger | B3: Threshold | C3: Action
A4: Services slowdown | B4: Growth below mid-single digits | C4: Re-underwrite thesis.
A5: Margin compression | B5: Gross margin down more than 150 bps | C5: Trim or exit paper position.
A6: Hardware guide-down | B6: Sustained device revenue decline | C6: Mark thesis weakened.

Sheet Source Notes
A1: AAPL Source Notes
A3: Evidence | B3: Value | C3: Source | D3: Implication
A4: What changed | B4: Apple reported FY2024 net sales of $391.0B. | C4: Apple FY2024 Form 10-K; cached SEC snapshot (2024-11-01) | D4: Defines why now and whether the thesis is reacting to a real change rather than a stale narrative.
A5: Management / filing narrative | B5: FY2024 revenue returned to modest growth after FY2023 contraction. | C5: Apple FY2024 Form 10-K; cached SEC snapshot (2024-11-01) | D5: Connects the thesis to company-disclosed operating context instead of only market price action.
A6: Risk / falsification | B6: Apple's risk disclosures emphasize competitive pressure, supply concentration, geopolitical and trade restrictions, dependence on third-party developers and distribution, and regulatory scrutiny of platform economics. | C6: Apple FY2024 Form 10-K; cached SEC snapshot (2024-11-01) | D6: Supplies explicit conditions that can weaken or break the thesis.
A7: Market debate | B7: The core debate is whether a large installed base, services mix, and product ecosystem can defend earnings power while hardware replacement cycles remain uneven and regulators scrutinize platform monetization. | C7: Citadail cached coverage seed | D7: Frames what the market is likely focused on versus what the thesis needs to prove.
A8: Business quality driver | B8: Apple generated $118.3B of operating cash flow and $108.8B of free cash flow in FY2024. | C8: Apple FY2024 Form 10-K; cached SEC snapshot (2024-11-01) | D8: Identifies the qualitative driver that must translate into durable model assumptions.
A9: FY2024 revenue base | B9: $391.0bn / 2.0% YoY | C9: Apple FY2024 Form 10-K; cached SEC snapshot filed 2024-11-01 | D9: Sets the growth bar the narrative must beat or defend.
A10: FY2024 margin structure | B10: Gross 46.2% / operating 31.5% | C10: Apple FY2024 Form 10-K; cached SEC snapshot filed 2024-11-01 | D10: Shows whether the qualitative story has already appeared in reported economics.
A11: FY2024 free cash flow | B11: $108.8bn / 27.8% margin | C11: Apple FY2024 Form 10-K; cached SEC snapshot filed 2024-11-01 | D11: Tests whether the company can fund reinvestment, buybacks, and downside resilience.
A12: FY2024 revenue | B12: $391.0bn | C12: Apple FY2024 Form 10-K | D12: Reported revenue growth resets the underwriting base after FY2023 pressure.
A13: FY2024 gross margin | B13: 46.2% | C13: Apple FY2024 Form 10-K | D13: Gross margin expansion supports the services mix and pricing discipline argument.
A14: FY2024 operating margin | B14: 31.5% | C14: Apple FY2024 Form 10-K | D14: Operating margin anchors the earnings durability case.
... A16: FY2024 net margin | B16: 24.0% | C16: Apple FY2024 Form 10-K | D16: Net margin converts the operating story into earnings power.
